<dialogue name="FirstQuest">
  <node id="0" npcText="Привет путник">
    <answer text="Как дела?" toNode="1" />
    <answer text="На счет задания" toNode="2" questValue="3" questName="FirstQuest" />
    <answer text="Есть Работенка?" toNode="3" questValue="0" questName="FirstQuest" />
    <answer text="Есть еще задания?" toNode="4" questValue="665" questName="FirstQuest" />
    <answer text="Тут это..." toNode="5" questValue="4" questName="WolfQuest" />
    <answer text="На счет задания" toNode="6" questValue="3" questName="WolfQuest" />
    <answer text="Птицы перестреляны" toNode="10" questStatus="3" questValue="2" questName="FirstQuest" />
    <answer text="Есть еще задания?" toNode="4" questValue="777" questName="FirstQuest" />
    <answer text="Пока" exit="True" />
  </node>
  <node id="1" npcText="Неплохо">
    <answer text="Понятно" toNode="0" />
    <answer text="Иди в жопу" exit="True" />
  </node>
  <node id="2" npcText="Да, что с заданием?">
    <answer text="Все готово" toNode="7" questStatus="3" questValue="3" questName="FirstQuest" />
    <answer text="Пока" exit="True" />
  </node>
  <node id="3" npcText="Да конечно, возьмешься?">
    <answer text="Да " exit="True" questStatus="1" questName="FirstQuest" />
    <answer text="Иди в жопу" exit="True" />
  </node>
  <node id="4" npcText="Тут волк неподалеку гуляет, надо бы от него избавиться, возьмешься?">
    <answer text="Да " exit="True" questStatus="1" questName="WolfQuest" />
    <answer text="Иди в жопу" exit="True" />
  </node>
  <node id="5" npcText="Ты че учудил, нафига ты волка к овцам привел. Лучше бы тебя ничему не просил.">
    <answer text="..." toNode="9" questStatus="3" questValueGreater="1" questName="WolfQuest" />
    <answer text="Пока" exit="True" />
  </node>
  <node id="6" npcText="Что там?">
    <answer text="Волк умер как и просил" toNode="8" questStatus="3" questValueGreater="3" questName="WolfQuest" />
    <answer text="Ничего, я лох" exit="True" />
  </node>
  <node id="7" npcText="Молодец вот тебе леденец">
    <answer text="Спасибо пока" exit="True" />
  </node>
  <node id="8" npcText="Вай какой молодец вот тебе еще леденец">
    <answer text="Спасибо пока" exit="True" />
  </node>
  <node id="9" npcText="Уйди отсюда чтобы глаза мои тебя больше не видели">
    <answer text="..." exit="True" />
  </node>
  <node id="10" npcText="Птицы которые вредят, то есть ворон дибил, а не куриц">
    <answer text="Курица не рыба, баба не человек, всем тебе не угодишь" exit="True" />
  </node>
</dialogue>